timetree_sdk/__init__.py
timetree_sdk/api.py
timetree_sdk/models/__init__.py
timetree_sdk/models/base.py
timetree_sdk/models/events.py
timetree_sdk/models/responses.py
tooniez_timetree_sdk-0.0.5.dist-info/METADATA
tooniez_timetree_sdk-0.0.5.dist-info/WHEEL
tooniez_timetree_sdk-0.0.5.dist-info/top_level.txt
tooniez_timetree_sdk-0.0.5.dist-info/RECORD
