Metadata-Version: 2.1
Name: tooniez-timetree-sdk
Version: 0.0.5
Summary: TimeTree SDK
Home-page: https://github.com/tooniez/tooniez-timetree-sdk
Author: tooniez
Author-email: tooni22@proton.me
License: MIT
Keywords: timetree api sdk
Platform: UNKNOWN
Classifier: Development Status :: 4 - Beta
Classifier: License :: OSI Approved :: MIT License
Classifier: Programming Language :: Python :: 3.8
Requires-Dist: requests
